README.md
setup.py
simple_slice_viewer/__init__.py
simple_slice_viewer/console.py
simple_slice_viewer/controller.py
simple_slice_viewer/controller_base.py
simple_slice_viewer/load_pet_view.py
simple_slice_viewer/logger.py
simple_slice_viewer/menus.py
simple_slice_viewer/model.py
simple_slice_viewer/movie_maker.py
simple_slice_viewer/preset_controllers.py
simple_slice_viewer/preset_model.py
simple_slice_viewer/preset_view.py
simple_slice_viewer/presets.yml
simple_slice_viewer/view.py
simple_slice_viewer/view_base.py
simple_slice_viewer.egg-info/PKG-INFO
simple_slice_viewer.egg-info/SOURCES.txt
simple_slice_viewer.egg-info/dependency_links.txt
simple_slice_viewer.egg-info/entry_points.txt
simple_slice_viewer.egg-info/not-zip-safe
simple_slice_viewer.egg-info/requires.txt
simple_slice_viewer.egg-info/top_level.txt
sitk_tools/__init__.py
sitk_tools/dicom_reader.py
sitk_tools/image.py
sitk_tools/statistics.py
sitk_tools/suv.py