Metadata-Version: 2.1
Name: simple-slice-viewer
Version: 0.97
Summary: Simple slice viewer for Simple ITK images
Author: M. Segbers
Author-email: m.segbers@gmail.com
License: MIT
Keywords: ImageViewer DICOM,SimpleITK
Classifier: Development Status :: 3 - Alpha
Classifier: License :: OSI Approved :: MIT License
Classifier: Programming Language :: Python :: 3.6
Classifier: Topic :: Scientific/Engineering :: Medical Science Apps.
Classifier: Intended Audience :: Science/Research
Classifier: Natural Language :: English
